icub_models/__init__.py
icub_models/icub_models.py
icub_models-3.1.0.data/data/share/iCub/conf/gazebo_icub_head_without_eyes.ini
icub_models-3.1.0.data/data/share/iCub/conf/gazebo_icub_inertial.ini
icub_models-3.1.0.data/data/share/iCub/conf/gazebo_icub_left_arm_inertial.ini
icub_models-3.1.0.data/data/share/iCub/conf/gazebo_icub_left_arm_no_hand_for_no_hand_model.ini
icub_models-3.1.0.data/data/share/iCub/conf/gazebo_icub_left_leg.ini
icub_models-3.1.0.data/data/share/iCub/conf/gazebo_icub_right_arm_inertial.ini
icub_models-3.1.0.data/data/share/iCub/conf/gazebo_icub_right_arm_no_hand_for_no_hand_model.ini
icub_models-3.1.0.data/data/share/iCub/conf/gazebo_icub_right_leg.ini
icub_models-3.1.0.data/data/share/iCub/conf/gazebo_icub_robotname.ini
icub_models-3.1.0.data/data/share/iCub/conf/gazebo_icub_torso.ini
icub_models-3.1.0.data/data/share/iCub/conf/gazebo_icub_xsens_inertial.ini
icub_models-3.1.0.data/data/share/iCub/conf/icub.xml
icub_models-3.1.0.data/data/share/iCub/conf/left_camera.ini
icub_models-3.1.0.data/data/share/iCub/conf/right_camera.ini
icub_models-3.1.0.data/data/share/iCub/conf/yarpmotorgui.ini
icub_models-3.1.0.data/data/share/iCub/conf/FT/gazebo_icub_left_arm_ft.ini
icub_models-3.1.0.data/data/share/iCub/conf/FT/gazebo_icub_left_foot_ft.ini
icub_models-3.1.0.data/data/share/iCub/conf/FT/gazebo_icub_left_leg_ft.ini
icub_models-3.1.0.data/data/share/iCub/conf/FT/gazebo_icub_right_arm_ft.ini
icub_models-3.1.0.data/data/share/iCub/conf/FT/gazebo_icub_right_foot_ft.ini
icub_models-3.1.0.data/data/share/iCub/conf/FT/gazebo_icub_right_leg_ft.ini
icub_models-3.1.0.data/data/share/iCub/conf/MTB/gazebo_icub_left_arm_mtb.ini
icub_models-3.1.0.data/data/share/iCub/conf/MTB/gazebo_icub_left_leg_mtb.ini
icub_models-3.1.0.data/data/share/iCub/conf/MTB/gazebo_icub_right_arm_mtb.ini
icub_models-3.1.0.data/data/share/iCub/conf/MTB/gazebo_icub_right_leg_mtb.ini
icub_models-3.1.0.data/data/share/iCub/conf/MTB/gazebo_icub_torso_mtb.ini
icub_models-3.1.0.dist-info/LICENSE
icub_models-3.1.0.dist-info/METADATA
icub_models-3.1.0.dist-info/WHEEL
icub_models-3.1.0.dist-info/top_level.txt
icub_models-3.1.0.dist-info/RECORD
