Metadata-Version: 2.1
Name: icub_models
Version: 3.1.0
Summary: Official URDF and SDF models of the iCub humanoid robot.
Home-page: https://github.com/robotology/icub-models
Author: Giulio Romualdi
Author-email: giulio.romualdi@gmail.com
License: Creative Commons Attribution Share Alike 4.0 International
Project-URL: Changelog, https://github.com/robotology/icub-models/releases
Project-URL: Tracker, https://github.com/robotology/icub-models/issues
Project-URL: Source, https://github.com/robotology/icub-models
Keywords: robotics,gazebo,urdf,ros,icub,gazebo-models,gazebo-simulators
Platform: any
Classifier: Development Status :: 5 - Production/Stable
Classifier: Operating System :: OS Independent
Classifier: Topic :: Games/Entertainment :: Simulation
Classifier: Topic :: Scientific/Engineering :: Physics
Classifier: Topic :: Software Development
Classifier: Framework :: Robot Framework
Classifier: Intended Audience :: Developers
Classifier: Intended Audience :: Science/Research
Classifier: Programming Language :: Python :: 3.8
Classifier: Programming Language :: Python :: 3.9
Classifier: Programming Language :: Python :: 3.10
Classifier: Programming Language :: Python :: 3 :: Only
Classifier: Programming Language :: Python :: Implementation :: CPython
Requires-Python: >=3.8
License-File: LICENSE
Provides-Extra: test
Requires-Dist: pytest; extra == "test"
Requires-Dist: black; extra == "test"
